rtl/spi_master.v
// Eight-bit, MSB-first, full-duplex SPI controller. One CS per byte, modes 0-3.
// All logic uses clk plus enables; SCK is an output, never an internal clock.
module spi_master (
    input wire clk, input wire rst, input wire valid,
    input wire [7:0] tx_data, input wire miso,
    input wire cpol, input wire cpha, input wire [15:0] half_period,
    output wire ready, output reg busy, output reg done, output reg config_error,
    output reg sck, output reg mosi, output reg cs_n, output reg [7:0] rx_data
);
    reg pol, phase, finishing;
    reg [15:0] divider, timer;
    reg [4:0] edge_count;
    reg [7:0] tx_shift, rx_shift;
    wire sample_edge = phase ? edge_count[0] : !edge_count[0];
    assign ready = !busy && !rst;
    always @(posedge clk) begin
        if (rst) begin
            busy <= 0; done <= 0; config_error <= 0;
            sck <= 0; mosi <= 0; cs_n <= 1; rx_data <= 0;
            pol <= 0; phase <= 0; finishing <= 0;
            divider <= 2; timer <= 0; edge_count <= 0;
            tx_shift <= 0; rx_shift <= 0;
        end else begin
            done <= 0; config_error <= 0;
            if (valid && ready) begin
                if (half_period < 2) begin
                    config_error <= 1;
                end else begin
                    pol <= cpol; phase <= cpha;
                    divider <= half_period; timer <= half_period - 1'b1;
                    busy <= 1; cs_n <= 0; sck <= cpol;
                    edge_count <= 0; finishing <= 0; rx_shift <= 0;
                    tx_shift <= cpha ? tx_data : {tx_data[6:0], 1'b0};
                    mosi <= cpha ? 1'b0 : tx_data[7];
                end
            end else if (busy) begin
                if (timer != 0) timer <= timer - 1'b1;
                else begin
                    timer <= divider - 1'b1;
                    if (finishing) begin
                        busy <= 0; cs_n <= 1; done <= 1;
                        rx_data <= rx_shift; sck <= pol;
                    end else begin
                        sck <= !sck;
                        if (sample_edge) rx_shift <= {rx_shift[6:0], miso};
                        else begin
                            mosi <= tx_shift[7];
                            tx_shift <= {tx_shift[6:0], 1'b0};
                        end
                        if (edge_count == 15) finishing <= 1;
                        else edge_count <= edge_count + 1'b1;
                    end
                end
            end else begin
                sck <= cpol; mosi <= 0;
            end
        end
    end
endmodule

tb/tb_spi.sv
`timescale 1ns/1ps
module tb_spi;
    reg clk=0,rst=1,valid=0,cpol=0,cpha=0,miso=0;
    reg [7:0] tx_data=0;
    reg [15:0] half_period=4;
    wire ready,busy,done,config_error,sck,mosi,cs_n;
    wire [7:0] rx_data;
    reg monitor_active=0, expected_pol=0,expected_phase=0;
    reg [7:0] expected_tx,reply,observed_tx;
    integer expected_half,edges=0,samples=0,checks=0,transfers=0;
    time last_edge,cs_start;
    bit smoke,waves;
    reg previous_done=0;
    reg [255:0] mode_bytes[0:3];
    reg [11:0] mode_dividers=0;
    string vcd_path;
    always #5 clk=!clk;
    spi_master dut(clk,rst,valid,tx_data,miso,cpol,cpha,half_period,ready,busy,done,config_error,sck,mosi,cs_n,rx_data);

    task automatic check(input bit condition,input string label);
        checks++;
        if(!condition) $fatal(1,"ASSERTION %s t=%0t",label,$time);
    endtask

    // Serial target model observes only public pins; no DUT internals.
    always @(negedge cs_n) if(monitor_active) begin
        edges=0; samples=0; observed_tx=0; cs_start=$time; last_edge=$time;
        miso = expected_phase ? 1'b0 : reply[7];
    end
    always @(sck) if(monitor_active && !cs_n && !rst && $time>cs_start) begin
        if(!smoke) check($time-last_edge==expected_half*10,"SPI exact half-period and CS setup");
        last_edge=$time; edges++;
        if((!expected_phase && sck!=expected_pol) || (expected_phase && sck==expected_pol)) begin
            check(samples<8,"SPI no extra sample edge");
            observed_tx[7-samples]=mosi;
            samples++;
        end else begin
            // Target changes MISO after launch edge, giving setup before sample edge.
            #1;
            if(samples<8) miso=reply[7-samples]; else miso=0;
        end
    end
    always @(posedge cs_n) if(monitor_active && !rst) begin
        check(edges==16 && samples==8,"SPI exactly eight full clock cycles");
        check(observed_tx===expected_tx,"SPI target observed correct MOSI bits");
        if(!smoke) check($time-last_edge>=expected_half*10,"SPI CS hold after last edge");
    end
    always @(posedge clk) begin
        #1;
        if(!rst) begin
            check(!(done && previous_done),"SPI done is one cycle");
            if(done) check(cs_n===1'b1 && ready===1'b1,"SPI done means deselected and ready");
        end
        previous_done=done;
    end

    task automatic reset_dut;
        monitor_active=0;
        @(negedge clk); rst=1; valid=0;
        repeat(3) @(negedge clk);
        check(cs_n===1'b1 && busy===1'b0 && sck===1'b0,"SPI reset idle");
        rst=0; repeat(3) @(negedge clk);
    endtask

    task automatic transfer(input integer mode,input integer divider,input reg[7:0] value,input reg[7:0] returned,input bit probe_busy);
        integer cycles;
        @(negedge clk);
        cpol=(mode>>1)&1; cpha=mode&1; half_period=divider; tx_data=value; valid=0;
        expected_pol=cpol; expected_phase=cpha; expected_half=divider;
        expected_tx=value; reply=returned;
        @(negedge clk);
        check(sck===expected_pol && cs_n===1'b1,"SPI idle CPOL");
        monitor_active=1; valid=1;
        @(posedge clk); #2;
        check(busy===1'b1 && cs_n===1'b0,"SPI request acceptance");
        cycles=0;
        while(!done && cycles<20*divider+20) begin
            @(negedge clk);
            if(probe_busy && cycles>=2*divider && cycles<2*divider+2) begin
                valid=1; cpol=!expected_pol; cpha=!expected_phase;
                half_period=divider+3; tx_data=~value;
            end else valid=0;
            @(posedge clk); #2; cycles++;
        end
        check(done===1'b1,"SPI bounded completion");
        check(rx_data===returned,"SPI received independent target response");
        check(sck===expected_pol && cs_n===1'b1,"SPI final clock and CS state");
        monitor_active=0; transfers++; mode_bytes[mode][value]=1;
        @(negedge clk); cpol=expected_pol; cpha=expected_phase; half_period=divider;
    endtask

    task automatic finish_report;
        integer m;
        $display("RESULT spi transfers=%0d checks=%0d",transfers,checks);
        for(m=0;m<4;m++) $display("COVER spi_mode%0d_bytes %0d 256",m,$countones(mode_bytes[m]));
        $display("COVER spi_mode_divider_cross %0d 12",$countones(mode_dividers));
        $display("VERIFICATION_PASS spi"); $finish;
    endtask

    integer m,d,b,divider;
    initial begin
        smoke=$test$plusargs("SMOKE"); waves=$test$plusargs("WAVES");
        for(m=0;m<4;m++) mode_bytes[m]=0;
        if($value$plusargs("VCD=%s",vcd_path)) begin $dumpfile(vcd_path); $dumpvars(0,tb_spi); end
        reset_dut();
        if(waves) begin
            for(m=0;m<4;m++) transfer(m,4,8'hA6,8'h3C,0);
            finish_report();
        end
        if(smoke) begin transfer(0,4,8'h00,8'h00,0); finish_report(); end
        for(m=0;m<4;m++) begin
            for(d=0;d<3;d++) begin
                case(d) 0: divider=2; 1: divider=3; default: divider=7; endcase
                for(b=0;b<256;b++) transfer(m,divider,b[7:0],b[7:0]^8'hA7,0);
                mode_dividers[m*3+d]=1;
            end
            transfer(m,3,8'h96,8'h69,1);
        end
        $display("COVER spi_busy_config_latch 4 4");
        // Invalid divisors cannot assert CS or begin a transaction.
        for(d=0;d<2;d++) begin
            @(negedge clk); half_period=d; valid=1;
            @(posedge clk); #2;
            check(config_error===1'b1 && cs_n===1'b1 && busy===1'b0,"SPI invalid divider rejected");
            @(negedge clk); valid=0;
        end
        $display("COVER spi_invalid_divider 2 2");
        // Abort mid-word. The target monitor is disabled for intentional reset.
        @(negedge clk); half_period=4; valid=1;
        repeat(8) @(negedge clk);
        reset_dut();
        repeat(20) @(negedge clk);
        check(!done && !busy && cs_n,"SPI reset abort no ghost completion");
        transfer(3,4,8'hC5,8'h5C,0);
        $display("COVER spi_reset_abort 1 1");
        check(&mode_dividers,"SPI mode-divider bins complete");
        for(m=0;m<4;m++) check(&mode_bytes[m],"SPI mode-byte bins complete");
        finish_report();
    end
    initial begin #20000000; $fatal(1,"ASSERTION global SPI watchdog timeout"); end
endmodule

runs/spi-waves/spi.vcd
$date
	Wed Sep  9 11:01:10 2026
$end
$version
	Icarus Verilog
$end
$timescale
	1ps
$end
$scope module tb_spi $end
$var wire 1 ! sck $end
$var wire 8 " rx_data [7:0] $end
$var wire 1 # ready $end
$var wire 1 $ mosi $end
$var wire 1 % done $end
$var wire 1 & cs_n $end
$var wire 1 ' config_error $end
$var wire 1 ( busy $end
$var reg 1 ) clk $end
$var reg 1 * cpha $end
$var reg 1 + cpol $end
$var reg 64 , cs_start [63:0] $end
$var reg 1 - expected_phase $end
$var reg 1 . expected_pol $end
$var reg 8 / expected_tx [7:0] $end
$var reg 16 0 half_period [15:0] $end
$var reg 64 1 last_edge [63:0] $end
$var reg 1 2 miso $end
$var reg 12 3 mode_dividers [11:0] $end
$var reg 1 4 monitor_active $end
$var reg 8 5 observed_tx [7:0] $end
$var reg 1 6 previous_done $end
$var reg 8 7 reply [7:0] $end
$var reg 1 8 rst $end
$var reg 8 9 tx_data [7:0] $end
$var reg 1 : valid $end
$var integer 32 ; b [31:0] $end
$var integer 32 < checks [31:0] $end
$var integer 32 = d [31:0] $end
$var integer 32 > divider [31:0] $end
$var integer 32 ? edges [31:0] $end
$var integer 32 @ expected_half [31:0] $end
$var integer 32 A m [31:0] $end
$var integer 32 B samples [31:0] $end
$var reg 1 C smoke $end
$var integer 32 D transfers [31:0] $end
$var reg 1 E waves $end
$scope module dut $end
$var wire 1 ) clk $end
$var wire 1 * cpha $end
$var wire 1 + cpol $end
$var wire 16 F half_period [15:0] $end
$var wire 1 2 miso $end
$var wire 1 # ready $end
$var wire 1 8 rst $end
$var wire 8 G tx_data [7:0] $end
$var wire 1 : valid $end
$var wire 1 H sample_edge $end
$var reg 1 ( busy $end
$var reg 1 ' config_error $end
$var reg 1 & cs_n $end
$var reg 16 I divider [15:0] $end
$var reg 1 % done $end
$var reg 5 J edge_count [4:0] $end
$var reg 1 K finishing $end
$var reg 1 $ mosi $end
$var reg 1 L phase $end
$var reg 1 M pol $end
$var reg 8 N rx_data [7:0] $end
$var reg 8 O rx_shift [7:0] $end
$var reg 1 ! sck $end
$var reg 16 P timer [15:0] $end
$var reg 8 Q tx_shift [7:0] $end
$upscope $end
$scope task check $end
$upscope $end
$scope task finish_report $end
$upscope $end
$scope task reset_dut $end
$upscope $end
$scope task transfer $end
$upscope $end
$upscope $end
$enddefinitions $end
$comment Show the parameter values. $end
$dumpall
$end
#0
$dumpvars
bx Q
bx P
bx O
bx N
xM
xL
xK
bx J
bx I
xH
b0 G
b100 F
1E
b0 D
0C
b0 B
b100 A
bx @
b0 ?
bx >
bx =
b0 <
bx ;
0:
b0 9
18
bx 7
06
bx 5
04
b0 3
02
bx 1
b100 0
bx /
0.
0-
bx ,
0+
0*
0)
x(
x'
x&
x%
x$
0#
bx "
x!
$end
#5000
1H
b0 O
b0 Q
b0 J
b0 P
b10 I
0K
0L
0M
b0 "
b0 N
1&
0$
0!
0'
0%
0(
1)
#10000
0)
#15000
1)
#20000
0)
#25000
1)
#30000
0)
#35000
1)
#40000
1#
08
b1 <
0)
#45000
1)
#46000
b10 <
#50000
0)
#55000
1)
#56000
b11 <
#60000
0)
#65000
1)
#66000
b100 <
#70000
b0 A
0)
#75000
1)
#76000
b101 <
#80000
b111100 7
b10100110 /
b100 @
b10100110 9
b10100110 G
0)
#85000
1)
#86000
b110 <
#90000
1:
14
b111 <
0)
#95000
b1011111 1
b1011111 ,
b0 5
0#
1$
b1001100 Q
0&
1(
b11 P
b100 I
1)
#96000
b1000 <
#97000
b1001 <
#100000
0:
0)
#105000
b10 P
1)
#106000
b1010 <
#110000
0)
#115000
b1 P
1)
#116000
b1011 <
#120000
0)
#125000
b0 P
1)
#126000
b1100 <
#130000
0)
#135000
0H
b1 B
b10000000 5
b1 ?
b10000111 1
b1110 <
b1 J
1!
b11 P
1)
#136000
b1111 <
#140000
0)
#145000
b10 P
1)
#146000
b10000 <
#150000
0)
#155000
b1 P
1)
#156000
b10001 <
#160000
0)
#165000
b0 P
1)
#166000
b10010 <
#170000
0)
#175000
1H
b10 ?
b10101111 1
b10011 <
b10 J
b10011000 Q
0$
0!
b11 P
1)
#176000
b10100 <
#180000
0)
#185000
b10 P
1)
#186000
b10101 <
#190000
0)
#195000
b1 P
1)
#196000
b10110 <
#200000
0)
#205000
b0 P
1)
#206000
b10111 <
#210000
0)
#215000
0H
b10 B
b11 ?
b11010111 1
b11001 <
b11 J
1!
b11 P
1)
#216000
b11010 <
#220000
0)
#225000
b10 P
1)
#226000
b11011 <
#230000
0)
#235000
b1 P
1)
#236000
b11100 <
#240000
0)
#245000
b0 P
1)
#246000
b11101 <
#250000
0)
#255000
1H
b100 ?
b11111111 1
b11110 <
b100 J
b110000 Q
1$
0!
b11 P
1)
#256000
12
b11111 <
#260000
0)
#265000
b10 P
1)
#266000
b100000 <
#270000
0)
#275000
b1 P
1)
#276000
b100001 <
#280000
0)
#285000
b0 P
1)
#286000
b100010 <
#290000
0)
#295000
0H
b11 B
b10100000 5
b101 ?
b100100111 1
b100100 <
b101 J
b1 O
1!
b11 P
1)
#296000
b100101 <
#300000
0)
#305000
b10 P
1)
#306000
b100110 <
#310000
0)
#315000
b1 P
1)
#316000
b100111 <
#320000
0)
#325000
b0 P
1)
#326000
b101000 <
#330000
0)
#335000
1H
b110 ?
b101001111 1
b101001 <
b110 J
b1100000 Q
0$
0!
b11 P
1)
#336000
b101010 <
#340000
0)
#345000
b10 P
1)
#346000
b101011 <
#350000
0)
#355000
b1 P
1)
#356000
b101100 <
#360000
0)
#365000
b0 P
1)
#366000
b101101 <
#370000
0)
#375000
0H
b100 B
b111 ?
b101110111 1
b101111 <
b111 J
b11 O
1!
b11 P
1)
#376000
b110000 <
#380000
0)
#385000
b10 P
1)
#386000
b110001 <
#390000
0)
#395000
b1 P
1)
#396000
b110010 <
#400000
0)
#405000
b0 P
1)
#406000
b110011 <
#410000
0)
#415000
1H
b1000 ?
b110011111 1
b110100 <
b1000 J
b11000000 Q
0!
b11 P
1)
#416000
b110101 <
#420000
0)
#425000
b10 P
1)
#426000
b110110 <
#430000
0)
#435000
b1 P
1)
#436000
b110111 <
#440000
0)
#445000
b0 P
1)
#446000
b111000 <
#450000
0)
#455000
0H
b101 B
b1001 ?
b111000111 1
b111010 <
b1001 J
b111 O
1!
b11 P
1)
#456000
b111011 <
#460000
0)
#465000
b10 P
1)
#466000
b111100 <
#470000
0)
#475000
b1 P
1)
#476000
b111101 <
#480000
0)
#485000
b0 P
1)
#486000
b111110 <
#490000
0)
#495000
1H
b1010 ?
b111101111 1
b111111 <
b1010 J
b10000000 Q
1$
0!
b11 P
1)
#496000
b1000000 <
#500000
0)
#505000
b10 P
1)
#506000
b1000001 <
#510000
0)
#515000
b1 P
1)
#516000
b1000010 <
#520000
0)
#525000
b0 P
1)
#526000
b1000011 <
#530000
0)
#535000
0H
b110 B
b10100100 5
b1011 ?
b1000010111 1
b1000101 <
b1011 J
b1111 O
1!
b11 P
1)
#536000
b1000110 <
#540000
0)
#545000
b10 P
1)
#546000
b1000111 <
#550000
0)
#555000
b1 P
1)
#556000
b1001000 <
#560000
0)
#565000
b0 P
1)
#566000
b1001001 <
#570000
0)
#575000
1H
b1100 ?
b1000111111 1
b1001010 <
b1100 J
b0 Q
0!
b11 P
1)
#576000
02
b1001011 <
#580000
0)
#585000
b10 P
1)
#586000
b1001100 <
#590000
0)
#595000
b1 P
1)
#596000
b1001101 <
#600000
0)
#605000
b0 P
1)
#606000
b1001110 <
#610000
0)
#615000
0H
b111 B
b10100110 5
b1101 ?
b1001100111 1
b1010000 <
b1101 J
b11110 O
1!
b11 P
1)
#616000
b1010001 <
#620000
0)
#625000
b10 P
1)
#626000
b1010010 <
#630000
0)
#635000
b1 P
1)
#636000
b1010011 <
#640000
0)
#645000
b0 P
1)
#646000
b1010100 <
#650000
0)
#655000
1H
b1110 ?
b1010001111 1
b1010101 <
b1110 J
0$
0!
b11 P
1)
#656000
b1010110 <
#660000
0)
#665000
b10 P
1)
#666000
b1010111 <
#670000
0)
#675000
b1 P
1)
#676000
b1011000 <
#680000
0)
#685000
b0 P
1)
#686000
b1011001 <
#690000
0)
#695000
0H
b1000 B
b1111 ?
b1010110111 1
b1011011 <
b1111 J
b111100 O
1!
b11 P
1)
#696000
b1011100 <
#700000
0)
#705000
b10 P
1)
#706000
b1011101 <
#710000
0)
#715000
b1 P
1)
#716000
b1011110 <
#720000
0)
#725000
b0 P
1)
#726000
b1011111 <
#730000
0)
#735000
b10000 ?
b1011011111 1
b1100000 <
1K
0!
b11 P
1)
#736000
b1100001 <
#740000
0)
#745000
b10 P
1)
#746000
b1100010 <
#750000
0)
#755000
b1 P
1)
#756000
b1100011 <
#760000
0)
#765000
b0 P
1)
#766000
b1100100 <
#770000
0)
#775000
b1100111 <
1#
b111100 "
b111100 N
1%
1&
0(
b11 P
1)
#776000
16
b1101001 <
#777000
b1 D
04
b1101100 <
#780000
b1 A
0)
#785000
0%
1)
#786000
06
b1101101 <
#790000
1-
1*
0)
#795000
1)
#796000
b1101110 <
#800000
1:
14
b1101111 <
0)
#805000
b1100100101 1
b1100100101 ,
b0 5
b0 B
b0 ?
0#
0H
b10100110 Q
b0 O
0K
b0 J
0&
1(
1L
1)
#806000
b1110000 <
#807000
b1110001 <
#810000
0:
0)
#815000
b10 P
1)
#816000
b1110010 <
#820000
0)
#825000
b1 P
1)
#826000
b1110011 <
#830000
0)
#835000
b0 P
1)
#836000
b1110100 <
#840000
0)
#845000
1H
b1 ?
b1101001101 1
b1110101 <
b1 J
b1001100 Q
1$
1!
b11 P
1)
#846000
b1110110 <
#850000
0)
#855000
b10 P
1)
#856000
b1110111 <
#860000
0)
#865000
b1 P
1)
#866000
b1111000 <
#870000
0)
#875000
b0 P
1)
#876000
b1111001 <
#880000
0)
#885000
0H
b1 B
b10000000 5
b10 ?
b1101110101 1
b1111011 <
b10 J
0!
b11 P
1)
#886000
b1111100 <
#890000
0)
#895000
b10 P
1)
#896000
b1111101 <
#900000
0)
#905000
b1 P
1)
#906000
b1111110 <
#910000
0)
#915000
b0 P
1)
#916000
b1111111 <
#920000
0)
#925000
1H
b11 ?
b1110011101 1
b10000000 <
b11 J
b10011000 Q
0$
1!
b11 P
1)
#926000
b10000001 <
#930000
0)
#935000
b10 P
1)
#936000
b10000010 <
#940000
0)
#945000
b1 P
1)
#946000
b10000011 <
#950000
0)
#955000
b0 P
1)
#956000
b10000100 <
#960000
0)
#965000
0H
b10 B
b100 ?
b1111000101 1
b10000110 <
b100 J
0!
b11 P
1)
#966000
b10000111 <
#970000
0)
#975000
b10 P
1)
#976000
b10001000 <
#980000
0)
#985000
b1 P
1)
#986000
b10001001 <
#990000
0)
#995000
b0 P
1)
#996000
b10001010 <
#1000000
0)
#1005000
1H
b101 ?
b1111101101 1
b10001011 <
b101 J
b110000 Q
1$
1!
b11 P
1)
#1006000
12
b10001100 <
#1010000
0)
#1015000
b10 P
1)
#1016000
b10001101 <
#1020000
0)
#1025000
b1 P
1)
#1026000
b10001110 <
#1030000
0)
#1035000
b0 P
1)
#1036000
b10001111 <
#1040000
0)
#1045000
0H
b11 B
b10100000 5
b110 ?
b10000010101 1
b10010001 <
b110 J
b1 O
0!
b11 P
1)
#1046000
b10010010 <
#1050000
0)
#1055000
b10 P
1)
#1056000
b10010011 <
#1060000
0)
#1065000
b1 P
1)
#1066000
b10010100 <
#1070000
0)
#1075000
b0 P
1)
#1076000
b10010101 <
#1080000
0)
#1085000
1H
b111 ?
b10000111101 1
b10010110 <
b111 J
b1100000 Q
0$
1!
b11 P
1)
#1086000
b10010111 <
#1090000
0)
#1095000
b10 P
1)
#1096000
b10011000 <
#1100000
0)
#1105000
b1 P
1)
#1106000
b10011001 <
#1110000
0)
#1115000
b0 P
1)
#1116000
b10011010 <
#1120000
0)
#1125000
0H
b100 B
b1000 ?
b10001100101 1
b10011100 <
b1000 J
b11 O
0!
b11 P
1)
#1126000
b10011101 <
#1130000
0)
#1135000
b10 P
1)
#1136000
b10011110 <
#1140000
0)
#1145000
b1 P
1)
#1146000
b10011111 <
#1150000
0)
#1155000
b0 P
1)
#1156000
b10100000 <
#1160000
0)
#1165000
1H
b1001 ?
b10010001101 1
b10100001 <
b1001 J
b11000000 Q
1!
b11 P
1)
#1166000
b10100010 <
#1170000
0)
#1175000
b10 P
1)
#1176000
b10100011 <
#1180000
0)
#1185000
b1 P
1)
#1186000
b10100100 <
#1190000
0)
#1195000
b0 P
1)
#1196000
b10100101 <
#1200000
0)
#1205000
0H
b101 B
b1010 ?
b10010110101 1
b10100111 <
b1010 J
b111 O
0!
b11 P
1)
#1206000
b10101000 <
#1210000
0)
#1215000
b10 P
1)
#1216000
b10101001 <
#1220000
0)
#1225000
b1 P
1)
#1226000
b10101010 <
#1230000
0)
#1235000
b0 P
1)
#1236000
b10101011 <
#1240000
0)
#1245000
1H
b1011 ?
b10011011101 1
b10101100 <
b1011 J
b10000000 Q
1$
1!
b11 P
1)
#1246000
b10101101 <
#1250000
0)
#1255000
b10 P
1)
#1256000
b10101110 <
#1260000
0)
#1265000
b1 P
1)
#1266000
b10101111 <
#1270000
0)
#1275000
b0 P
1)
#1276000
b10110000 <
#1280000
0)
#1285000
0H
b110 B
b10100100 5
b1100 ?
b10100000101 1
b10110010 <
b1100 J
b1111 O
0!
b11 P
1)
#1286000
b10110011 <
#1290000
0)
#1295000
b10 P
1)
#1296000
b10110100 <
#1300000
0)
#1305000
b1 P
1)
#1306000
b10110101 <
#1310000
0)
#1315000
b0 P
1)
#1316000
b10110110 <
#1320000
0)
#1325000
1H
b1101 ?
b10100101101 1
b10110111 <
b1101 J
b0 Q
1!
b11 P
1)
#1326000
02
b10111000 <
#1330000
0)
#1335000
b10 P
1)
#1336000
b10111001 <
#1340000
0)
#1345000
b1 P
1)
#1346000
b10111010 <
#1350000
0)
#1355000
b0 P
1)
#1356000
b10111011 <
#1360000
0)
#1365000
0H
b111 B
b10100110 5
b1110 ?
b10101010101 1
b10111101 <
b1110 J
b11110 O
0!
b11 P
1)
#1366000
b10111110 <
#1370000
0)
#1375000
b10 P
1)
#1376000
b10111111 <
#1380000
0)
#1385000
b1 P
1)
#1386000
b11000000 <
#1390000
0)
#1395000
b0 P
1)
#1396000
b11000001 <
#1400000
0)
#1405000
1H
b1111 ?
b10101111101 1
b11000010 <
b1111 J
0$
1!
b11 P
1)
#1406000
b11000011 <
#1410000
0)
#1415000
b10 P
1)
#1416000
b11000100 <
#1420000
0)
#1425000
b1 P
1)
#1426000
b11000101 <
#1430000
0)
#1435000
b0 P
1)
#1436000
b11000110 <
#1440000
0)
#1445000
b1000 B
b10000 ?
b10110100101 1
b11001000 <
1K
b111100 O
0!
b11 P
1)
#1446000
b11001001 <
#1450000
0)
#1455000
b10 P
1)
#1456000
b11001010 <
#1460000
0)
#1465000
b1 P
1)
#1466000
b11001011 <
#1470000
0)
#1475000
b0 P
1)
#1476000
b11001100 <
#1480000
0)
#1485000
b11001111 <
1#
1%
1&
0(
b11 P
1)
#1486000
16
b11010001 <
#1487000
b10 D
04
b11010100 <
#1490000
b10 A
0)
#1495000
0%
1)
#1496000
06
b11010101 <
#1500000
0-
1.
0*
1+
0)
#1505000
1!
1)
#1506000
b11010110 <
#1510000
1:
14
b11010111 <
0)
#1515000
b10111101011 1
b10111101011 ,
b0 5
b0 B
b0 ?
0#
1H
1$
b1001100 Q
b0 O
0K
b0 J
0&
1(
0L
1M
1)
#1516000
b11011000 <
#1517000
b11011001 <
#1520000
0:
0)
#1525000
b10 P
1)
#1526000
b11011010 <
#1530000
0)
#1535000
b1 P
1)
#1536000
b11011011 <
#1540000
0)
#1545000
b0 P
1)
#1546000
b11011100 <
#1550000
0)
#1555000
0H
b1 B
b10000000 5
b1 ?
b11000010011 1
b11011110 <
b1 J
0!
b11 P
1)
#1556000
b11011111 <
#1560000
0)
#1565000
b10 P
1)
#1566000
b11100000 <
#1570000
0)
#1575000
b1 P
1)
#1576000
b11100001 <
#1580000
0)
#1585000
b0 P
1)
#1586000
b11100010 <
#1590000
0)
#1595000
1H
b10 ?
b11000111011 1
b11100011 <
b10 J
b10011000 Q
0$
1!
b11 P
1)
#1596000
b11100100 <
#1600000
0)
#1605000
b10 P
1)
#1606000
b11100101 <
#1610000
0)
#1615000
b1 P
1)
#1616000
b11100110 <
#1620000
0)
#1625000
b0 P
1)
#1626000
b11100111 <
#1630000
0)
#1635000
0H
b10 B
b11 ?
b11001100011 1
b11101001 <
b11 J
0!
b11 P
1)
#1636000
b11101010 <
#1640000
0)
#1645000
b10 P
1)
#1646000
b11101011 <
#1650000
0)
#1655000
b1 P
1)
#1656000
b11101100 <
#1660000
0)
#1665000
b0 P
1)
#1666000
b11101101 <
#1670000
0)
#1675000
1H
b100 ?
b11010001011 1
b11101110 <
b100 J
b110000 Q
1$
1!
b11 P
1)
#1676000
12
b11101111 <
#1680000
0)
#1685000
b10 P
1)
#1686000
b11110000 <
#1690000
0)
#1695000
b1 P
1)
#1696000
b11110001 <
#1700000
0)
#1705000
b0 P
1)
#1706000
b11110010 <
#1710000
0)
#1715000
0H
b11 B
b10100000 5
b101 ?
b11010110011 1
b11110100 <
b101 J
b1 O
0!
b11 P
1)
#1716000
b11110101 <
#1720000
0)
#1725000
b10 P
1)
#1726000
b11110110 <
#1730000
0)
#1735000
b1 P
1)
#1736000
b11110111 <
#1740000
0)
#1745000
b0 P
1)
#1746000
b11111000 <
#1750000
0)
#1755000
1H
b110 ?
b11011011011 1
b11111001 <
b110 J
b1100000 Q
0$
1!
b11 P
1)
#1756000
b11111010 <
#1760000
0)
#1765000
b10 P
1)
#1766000
b11111011 <
#1770000
0)
#1775000
b1 P
1)
#1776000
b11111100 <
#1780000
0)
#1785000
b0 P
1)
#1786000
b11111101 <
#1790000
0)
#1795000
0H
b100 B
b111 ?
b11100000011 1
b11111111 <
b111 J
b11 O
0!
b11 P
1)
#1796000
b100000000 <
#1800000
0)
#1805000
b10 P
1)
#1806000
b100000001 <
#1810000
0)
#1815000
b1 P
1)
#1816000
b100000010 <
#1820000
0)
#1825000
b0 P
1)
#1826000
b100000011 <
#1830000
0)
#1835000
1H
b1000 ?
b11100101011 1
b100000100 <
b1000 J
b11000000 Q
1!
b11 P
1)
#1836000
b100000101 <
#1840000
0)
#1845000
b10 P
1)
#1846000
b100000110 <
#1850000
0)
#1855000
b1 P
1)
#1856000
b100000111 <
#1860000
0)
#1865000
b0 P
1)
#1866000
b100001000 <
#1870000
0)
#1875000
0H
b101 B
b1001 ?
b11101010011 1
b100001010 <
b1001 J
b111 O
0!
b11 P
1)
#1876000
b100001011 <
#1880000
0)
#1885000
b10 P
1)
#1886000
b100001100 <
#1890000
0)
#1895000
b1 P
1)
#1896000
b100001101 <
#1900000
0)
#1905000
b0 P
1)
#1906000
b100001110 <
#1910000
0)
#1915000
1H
b1010 ?
b11101111011 1
b100001111 <
b1010 J
b10000000 Q
1$
1!
b11 P
1)
#1916000
b100010000 <
#1920000
0)
#1925000
b10 P
1)
#1926000
b100010001 <
#1930000
0)
#1935000
b1 P
1)
#1936000
b100010010 <
#1940000
0)
#1945000
b0 P
1)
#1946000
b100010011 <
#1950000
0)
#1955000
0H
b110 B
b10100100 5
b1011 ?
b11110100011 1
b100010101 <
b1011 J
b1111 O
0!
b11 P
1)
#1956000
b100010110 <
#1960000
0)
#1965000
b10 P
1)
#1966000
b100010111 <
#1970000
0)
#1975000
b1 P
1)
#1976000
b100011000 <
#1980000
0)
#1985000
b0 P
1)
#1986000
b100011001 <
#1990000
0)
#1995000
1H
b1100 ?
b11111001011 1
b100011010 <
b1100 J
b0 Q
1!
b11 P
1)
#1996000
02
b100011011 <
#2000000
0)
#2005000
b10 P
1)
#2006000
b100011100 <
#2010000
0)
#2015000
b1 P
1)
#2016000
b100011101 <
#2020000
0)
#2025000
b0 P
1)
#2026000
b100011110 <
#2030000
0)
#2035000
0H
b111 B
b10100110 5
b1101 ?
b11111110011 1
b100100000 <
b1101 J
b11110 O
0!
b11 P
1)
#2036000
b100100001 <
#2040000
0)
#2045000
b10 P
1)
#2046000
b100100010 <
#2050000
0)
#2055000
b1 P
1)
#2056000
b100100011 <
#2060000
0)
#2065000
b0 P
1)
#2066000
b100100100 <
#2070000
0)
#2075000
1H
b1110 ?
b100000011011 1
b100100101 <
b1110 J
0$
1!
b11 P
1)
#2076000
b100100110 <
#2080000
0)
#2085000
b10 P
1)
#2086000
b100100111 <
#2090000
0)
#2095000
b1 P
1)
#2096000
b100101000 <
#2100000
0)
#2105000
b0 P
1)
#2106000
b100101001 <
#2110000
0)
#2115000
0H
b1000 B
b1111 ?
b100001000011 1
b100101011 <
b1111 J
b111100 O
0!
b11 P
1)
#2116000
b100101100 <
#2120000
0)
#2125000
b10 P
1)
#2126000
b100101101 <
#2130000
0)
#2135000
b1 P
1)
#2136000
b100101110 <
#2140000
0)
#2145000
b0 P
1)
#2146000
b100101111 <
#2150000
0)
#2155000
b10000 ?
b100001101011 1
b100110000 <
1K
1!
b11 P
1)
#2156000
b100110001 <
#2160000
0)
#2165000
b10 P
1)
#2166000
b100110010 <
#2170000
0)
#2175000
b1 P
1)
#2176000
b100110011 <
#2180000
0)
#2185000
b0 P
1)
#2186000
b100110100 <
#2190000
0)
#2195000
b100110111 <
1#
1%
1&
0(
b11 P
1)
#2196000
16
b100111001 <
#2197000
b11 D
04
b100111100 <
#2200000
b11 A
0)
#2205000
0%
1)
#2206000
06
b100111101 <
#2210000
1-
1*
0)
#2215000
1)
#2216000
b100111110 <
#2220000
1:
14
b100111111 <
0)
#2225000
b100010110001 1
b100010110001 ,
b0 5
b0 B
b0 ?
0#
0H
b10100110 Q
b0 O
0K
b0 J
0&
1(
1L
1)
#2226000
b101000000 <
#2227000
b101000001 <
#2230000
0:
0)
#2235000
b10 P
1)
#2236000
b101000010 <
#2240000
0)
#2245000
b1 P
1)
#2246000
b101000011 <
#2250000
0)
#2255000
b0 P
1)
#2256000
b101000100 <
#2260000
0)
#2265000
1H
b1 ?
b100011011001 1
b101000101 <
b1 J
b1001100 Q
1$
0!
b11 P
1)
#2266000
b101000110 <
#2270000
0)
#2275000
b10 P
1)
