rtl/uart_rx.v
// UART 8N1 receiver: two-flop synchronization, midpoint sampling, one-cycle events.
// Integration contract: CLKS_PER_BIT >= 16. No FIFO or receive backpressure.
// Synchronous active-high reset. Default regression checks dividers 16, 17 and 32.
module uart_rx #(
    parameter integer CLKS_PER_BIT = 16
) (
    input wire clk, input wire rst, input wire rx,
    output reg [7:0] data, output reg valid, output reg framing_error,
    output wire busy
);
    localparam integer TW = (CLKS_PER_BIT > 1) ? $clog2(CLKS_PER_BIT) : 1;
    localparam [2:0] IDLE=0, START=1, DATA=2, STOP=3, WAIT_HIGH=4;
    reg [2:0] state;
    (* ASYNC_REG = "TRUE" *) reg rx_meta, rx_sync;
    reg [TW-1:0] timer;
    reg [2:0] bit_index;
    reg [7:0] shift;
    assign busy = (state != IDLE);
    always @(posedge clk) begin
        if (rst) begin rx_meta <= 1; rx_sync <= 1; end
        else begin rx_meta <= rx; rx_sync <= rx_meta; end
    end
    always @(posedge clk) begin
        if (rst) begin
            state <= IDLE; timer <= 0; bit_index <= 0; shift <= 0;
            data <= 0; valid <= 0; framing_error <= 0;
        end else begin
            valid <= 0; framing_error <= 0;
            case (state)
                IDLE: if (!rx_sync) begin
                    timer <= CLKS_PER_BIT/2 - 1; state <= START;
                end
                START: if (timer != 0) timer <= timer - 1'b1;
                else if (!rx_sync) begin
                    timer <= CLKS_PER_BIT - 1; bit_index <= 0; state <= DATA;
                end else state <= IDLE;
                DATA: if (timer != 0) timer <= timer - 1'b1;
                else begin
                    shift[bit_index] <= rx_sync;
                    timer <= CLKS_PER_BIT - 1;
                    if (bit_index == 7) state <= STOP;
                    else bit_index <= bit_index + 1'b1;
                end
                STOP: if (timer != 0) timer <= timer - 1'b1;
                else begin
                    if (rx_sync) begin data <= shift; valid <= 1; state <= IDLE; end
                    else begin framing_error <= 1; state <= WAIT_HIGH; end
                end
                WAIT_HIGH: if (rx_sync) state <= IDLE;
                default: state <= IDLE;
            endcase
        end
    end
endmodule

rtl/uart_tx.v
// UART 8N1 transmitter. Data is accepted on valid && ready at the clock edge.
module uart_tx #(
    parameter integer CLKS_PER_BIT = 16
) (
    input wire clk, input wire rst,
    input wire valid, input wire [7:0] data,
    output wire ready, output wire tx,
    output reg busy, output reg done
);
    localparam integer TW = (CLKS_PER_BIT > 1) ? $clog2(CLKS_PER_BIT) : 1;
    reg [TW-1:0] timer;
    reg [3:0] bit_index;
    reg [9:0] frame;
    assign ready = !busy && !rst;
    assign tx = busy ? frame[0] : 1'b1;
    always @(posedge clk) begin
        if (rst) begin
            timer <= 0; bit_index <= 0; frame <= 10'h3ff;
            busy <= 0; done <= 0;
        end else begin
            done <= 0;
            if (valid && ready) begin
                frame <= {1'b1, data, 1'b0};
                timer <= CLKS_PER_BIT - 1;
                bit_index <= 0;
                busy <= 1;
            end else if (busy) begin
                if (timer == 0) begin
                    timer <= CLKS_PER_BIT - 1;
                    if (bit_index == 9) begin
                        busy <= 0; done <= 1;
                    end else begin
                        frame <= {1'b1, frame[9:1]};
                        bit_index <= bit_index + 1'b1;
                    end
                end else timer <= timer - 1'b1;
            end
        end
    end
endmodule

tb/tb_uart.sv
`timescale 1ns/1ps
module tb_uart;
    parameter integer DIV = 16;
    reg clk=0, rst=1, tx_valid=0, rx_line=1;
    reg [7:0] tx_data=0;
    wire tx_ready, tx_line, tx_busy, tx_done, rx_valid, rx_error, rx_busy;
    wire [7:0] rx_data;
    integer tx_frames=0, rx_frames=0, errors=0, checks=0;
    integer rx_events=0, error_events=0;
    reg [7:0] last_received;
    reg prev_rx_valid=0, prev_error=0, prev_done=0;
    bit smoke, waves;
    reg [255:0] tx_seen=0, rx_seen=0;
    string vcd_path;
    always #5 clk = !clk;
    uart_tx #(.CLKS_PER_BIT(DIV)) u_tx(clk,rst,tx_valid,tx_data,tx_ready,tx_line,tx_busy,tx_done);
    uart_rx #(.CLKS_PER_BIT(DIV)) u_rx(clk,rst,rx_line,rx_data,rx_valid,rx_error,rx_busy);

    task automatic check(input bit condition, input string label);
        checks++;
        if (!condition) $fatal(1,"ASSERTION %s t=%0t",label,$time);
    endtask

    always @(posedge clk) begin
        #1;
        if (!rst) begin
            check(!(rx_valid && prev_rx_valid),"UART RX valid must be one cycle");
            check(!(rx_error && prev_error),"UART framing error must be one cycle");
            check(!(tx_done && prev_done),"UART TX done must be one cycle");
            check(!(rx_valid && rx_error),"RX valid and framing error are exclusive");
            if (rx_valid) begin rx_events++; last_received=rx_data; end
            if (rx_error) error_events++;
        end
        prev_rx_valid=rx_valid; prev_error=rx_error; prev_done=tx_done;
    end

    task automatic reset_dut;
        @(negedge clk); rst=1; tx_valid=0; rx_line=1;
        repeat(3) @(negedge clk);
        check(tx_line===1'b1 && tx_ready===1'b0 && tx_busy===1'b0,"TX reset idle");
        rst=0;
        repeat(4) @(negedge clk);
        check(tx_ready===1'b1 && !rx_busy,"UART ready after reset");
    endtask

    // Reference is the frame definition and clock count, not DUT state/registers.
    task automatic transmit(input reg [7:0] value, input bit busy_probe);
        integer cycle, bit_number;
        reg expected;
        @(negedge clk); tx_data=value; tx_valid=1;
        @(posedge clk); #2;
        check(tx_busy===1'b1 && tx_ready===1'b0,"TX accepted request");
        for(cycle=0;cycle<10*DIV;cycle++) begin
            bit_number=cycle/DIV;
            if(bit_number==0) expected=0;
            else if(bit_number==9) expected=1;
            else expected=value[bit_number-1];
            if(!smoke || cycle% DIV == DIV/2)
                check(tx_line===expected,"TX framing, bit order, and divider");
            if(!smoke) check(tx_busy===1'b1 && tx_done===1'b0,"TX full frame duration");
            @(negedge clk);
            if(busy_probe && cycle>=3*DIV && cycle<3*DIV+2) begin
                tx_data=~value; tx_valid=1;
            end else tx_valid=0;
            @(posedge clk); #2;
        end
        check(tx_done===1'b1 && tx_ready===1'b1 && tx_line===1'b1,"TX completion and stop length");
        tx_seen[value]=1; tx_frames++;
        @(negedge clk);
    endtask

    // Independent serial source; period can differ from the DUT's nominal divider.
    task automatic receive(input reg [7:0] value, input integer bit_ns, input bit good_stop);
        integer b, before_rx, before_error;
        before_rx=rx_events; before_error=error_events;
        rx_line=0; #(bit_ns);
        for(b=0;b<8;b++) begin rx_line=value[b]; #(bit_ns); end
        rx_line=good_stop; #(bit_ns);
        rx_line=1;
        if(good_stop) begin
            check(rx_events==before_rx+1,"RX exactly one byte event");
            check(last_received===value,"RX payload from independent serial source");
            check(error_events==before_error,"RX good frame has no framing error");
            rx_seen[value]=1; rx_frames++;
        end else begin
            check(rx_events==before_rx,"RX bad stop does not produce valid data");
            check(error_events==before_error+1,"RX bad stop raises framing error");
            errors++;
            #(2*DIV*10);
        end
    endtask

    task automatic finish_report;
        $display("RESULT uart div=%0d tx_frames=%0d rx_frames=%0d framing_cases=%0d checks=%0d",DIV,tx_frames,rx_frames,errors,checks);
        $display("COVER uart_tx_bytes %0d 256",$countones(tx_seen));
        $display("COVER uart_rx_bytes %0d 256",$countones(rx_seen));
        $display("VERIFICATION_PASS uart");
        $finish;
    endtask

    integer k, before_rx, before_error;
    initial begin
        smoke=$test$plusargs("SMOKE"); waves=$test$plusargs("WAVES");
        if(DIV<16) $fatal(1,"CONFIG CLKS_PER_BIT must be >=16");
        if($value$plusargs("VCD=%s",vcd_path)) begin $dumpfile(vcd_path); $dumpvars(0,tb_uart); end
        reset_dut();
        if(waves) begin transmit(8'hA6,0); #3; receive(8'h3C,DIV*10,1); finish_report(); end
        if(smoke) begin transmit(8'h00,0); #3; receive(8'h00,DIV*10,1); finish_report(); end
        for(k=0;k<256;k++) transmit(k[7:0],0);
        transmit(8'h96,1);
        $display("COVER uart_busy_request 1 1");
        // All bytes, without inserted idle gaps: a continuous 8N1 receive stream.
        #3;
        for(k=0;k<256;k++) receive(k[7:0],DIV*10,1);
        $display("COVER uart_back_to_back 1 1");
        #(2*DIV*10);
        receive(8'hA6,(DIV*10*98)/100,1);
        #(2*DIV*10);
        receive(8'h69,(DIV*10*102)/100,1);
        $display("COVER uart_period_offsets 2 2");
        #(2*DIV*10); receive(8'h5A,DIV*10,0);
        $display("COVER uart_bad_stop 1 1");
        before_rx=rx_events; before_error=error_events;
        rx_line=0; #(DIV*10/4); rx_line=1; #(12*DIV*10);
        check(rx_events==before_rx && error_events==before_error,"RX rejects short false start");
        $display("COVER uart_false_start 1 1");
        before_rx=rx_events; before_error=error_events;
        rx_line=0; #(30*DIV*10); rx_line=1; #(2*DIV*10);
        check(rx_events==before_rx && error_events==before_error+1,"RX break produces one error then waits for HIGH");
        receive(8'hC3,DIV*10,1);
        $display("COVER uart_break_recovery 1 1");
        // Abort a TX and an RX in progress with synchronous reset.
        @(negedge clk); tx_valid=1; tx_data=8'hA5; rx_line=0;
        repeat(3*DIV) @(negedge clk);
        reset_dut();
        before_rx=rx_events; #(12*DIV*10);
        check(rx_events==before_rx,"Reset abort produces no ghost receive");
        transmit(8'hD2,0); #3; receive(8'h2D,DIV*10,1);
        $display("COVER uart_reset_abort 1 1");
        check(&tx_seen && &rx_seen,"Full byte-value coverage reached");
        finish_report();
    end
    initial begin #20000000; $fatal(1,"ASSERTION global UART watchdog timeout"); end
endmodule

runs/uart-waves/uart.vcd
$date
	Wed Sep  9 11:01:10 2026
$end
$version
	Icarus Verilog
$end
$timescale
	1ps
$end
$scope module tb_uart $end
$var wire 1 ! tx_ready $end
$var wire 1 " tx_line $end
$var wire 1 # tx_done $end
$var wire 1 $ tx_busy $end
$var wire 1 % rx_valid $end
$var wire 1 & rx_error $end
$var wire 8 ' rx_data [7:0] $end
$var wire 1 ( rx_busy $end
$var parameter 32 ) DIV $end
$var reg 1 * clk $end
$var reg 8 + last_received [7:0] $end
$var reg 1 , prev_done $end
$var reg 1 - prev_error $end
$var reg 1 . prev_rx_valid $end
$var reg 1 / rst $end
$var reg 1 0 rx_line $end
$var reg 256 1 rx_seen [255:0] $end
$var reg 8 2 tx_data [7:0] $end
$var reg 256 3 tx_seen [255:0] $end
$var reg 1 4 tx_valid $end
$var integer 32 5 before_error [31:0] $end
$var integer 32 6 before_rx [31:0] $end
$var integer 32 7 checks [31:0] $end
$var integer 32 8 error_events [31:0] $end
$var integer 32 9 errors [31:0] $end
$var integer 32 : k [31:0] $end
$var integer 32 ; rx_events [31:0] $end
$var integer 32 < rx_frames [31:0] $end
$var reg 1 = smoke $end
$var integer 32 > tx_frames [31:0] $end
$var reg 1 ? waves $end
$scope module u_rx $end
$var wire 1 * clk $end
$var wire 1 / rst $end
$var wire 1 0 rx $end
$var wire 1 ( busy $end
$var parameter 32 @ CLKS_PER_BIT $end
$var parameter 3 A DATA $end
$var parameter 3 B IDLE $end
$var parameter 3 C START $end
$var parameter 3 D STOP $end
$var parameter 32 E TW $end
$var parameter 3 F WAIT_HIGH $end
$var reg 3 G bit_index [2:0] $end
$var reg 8 H data [7:0] $end
$var reg 1 & framing_error $end
$var reg 1 I rx_meta $end
$var reg 1 J rx_sync $end
$var reg 8 K shift [7:0] $end
$var reg 3 L state [2:0] $end
$var reg 4 M timer [3:0] $end
$var reg 1 % valid $end
$upscope $end
$scope module u_tx $end
$var wire 1 * clk $end
$var wire 8 N data [7:0] $end
$var wire 1 ! ready $end
$var wire 1 / rst $end
$var wire 1 4 valid $end
$var wire 1 " tx $end
$var parameter 32 O CLKS_PER_BIT $end
$var parameter 32 P TW $end
$var reg 4 Q bit_index [3:0] $end
$var reg 1 $ busy $end
$var reg 1 # done $end
$var reg 10 R frame [9:0] $end
$var reg 4 S timer [3:0] $end
$upscope $end
$scope task check $end
$upscope $end
$scope task finish_report $end
$upscope $end
$scope task receive $end
$upscope $end
$scope task reset_dut $end
$upscope $end
$scope task transmit $end
$upscope $end
$upscope $end
$enddefinitions $end
$comment Show the parameter values. $end
$dumpall
b100 P
b10000 O
b100 F
b100 E
b11 D
b1 C
b0 B
b10 A
b10000 @
b10000 )
$end
#0
$dumpvars
bx S
bx R
bx Q
b0 N
bx M
bx L
bx K
xJ
xI
bx H
bx G
1?
b0 >
0=
b0 <
b0 ;
bx :
b0 9
b0 8
b0 7
bx 6
bx 5
04
b0 3
b0 2
b0 1
10
1/
0.
0-
0,
bx +
0*
x(
bx '
x&
x%
x$
x#
x"
0!
$end
#5000
1"
0#
0$
b1111111111 R
b0 Q
b0 S
1J
1I
0&
0%
b0 '
b0 H
b0 K
b0 G
b0 M
0(
b0 L
1*
#10000
0*
#15000
1*
#20000
0*
#25000
1*
#30000
0*
#35000
1*
#40000
1!
0/
b1 7
0*
#45000
1*
#46000
b101 7
#50000
0*
#55000
1*
#56000
b1001 7
#60000
0*
#65000
1*
#66000
b1101 7
#70000
0*
#75000
1*
#76000
b10001 7
#80000
b10010 7
0*
#85000
1*
#86000
b10110 7
#90000
14
b10100110 2
b10100110 N
0*
#95000
0!
0"
1$
b1111 S
b1101001100 R
1*
#96000
b11010 7
#97000
b11101 7
#100000
04
0*
#105000
b1110 S
1*
#106000
b100001 7
#107000
b100011 7
#110000
0*
#115000
b1101 S
1*
#116000
b100111 7
#117000
b101001 7
#120000
0*
#125000
b1100 S
1*
#126000
b101101 7
#127000
b101111 7
#130000
0*
#135000
b1011 S
1*
#136000
b110011 7
#137000
b110101 7
#140000
0*
#145000
b1010 S
1*
#146000
b111001 7
#147000
b111011 7
#150000
0*
#155000
b1001 S
1*
#156000
b111111 7
#157000
b1000001 7
#160000
0*
#165000
b1000 S
1*
#166000
b1000101 7
#167000
b1000111 7
#170000
0*
#175000
b111 S
1*
#176000
b1001011 7
#177000
b1001101 7
#180000
0*
#185000
b110 S
1*
#186000
b1010001 7
#187000
b1010011 7
#190000
0*
#195000
b101 S
1*
#196000
b1010111 7
#197000
b1011001 7
#200000
0*
#205000
b100 S
1*
#206000
b1011101 7
#207000
b1011111 7
#210000
0*
#215000
b11 S
1*
#216000
b1100011 7
#217000
b1100101 7
#220000
0*
#225000
b10 S
1*
#226000
b1101001 7
#227000
b1101011 7
#230000
0*
#235000
b1 S
1*
#236000
b1101111 7
#237000
b1110001 7
#240000
0*
#245000
b0 S
1*
#246000
b1110101 7
#247000
b1110111 7
#250000
0*
#255000
b1 Q
b1110100110 R
b1111 S
1*
#256000
b1111011 7
#257000
b1111101 7
#260000
0*
#265000
b1110 S
1*
#266000
b10000001 7
#267000
b10000011 7
#270000
0*
#275000
b1101 S
1*
#276000
b10000111 7
#277000
b10001001 7
#280000
0*
#285000
b1100 S
1*
#286000
b10001101 7
#287000
b10001111 7
#290000
0*
#295000
b1011 S
1*
#296000
b10010011 7
#297000
b10010101 7
#300000
0*
#305000
b1010 S
1*
#306000
b10011001 7
#307000
b10011011 7
#310000
0*
#315000
b1001 S
1*
#316000
b10011111 7
#317000
b10100001 7
#320000
0*
#325000
b1000 S
1*
#326000
b10100101 7
#327000
b10100111 7
#330000
0*
#335000
b111 S
1*
#336000
b10101011 7
#337000
b10101101 7
#340000
0*
#345000
b110 S
1*
#346000
b10110001 7
#347000
b10110011 7
#350000
0*
#355000
b101 S
1*
#356000
b10110111 7
#357000
b10111001 7
#360000
0*
#365000
b100 S
1*
#366000
b10111101 7
#367000
b10111111 7
#370000
0*
#375000
b11 S
1*
#376000
b11000011 7
#377000
b11000101 7
#380000
0*
#385000
b10 S
1*
#386000
b11001001 7
#387000
b11001011 7
#390000
0*
#395000
b1 S
1*
#396000
b11001111 7
#397000
b11010001 7
#400000
0*
#405000
b0 S
1*
#406000
b11010101 7
#407000
b11010111 7
#410000
0*
#415000
1"
b10 Q
b1111010011 R
b1111 S
1*
#416000
b11011011 7
#417000
b11011101 7
#420000
0*
#425000
b1110 S
1*
#426000
b11100001 7
#427000
b11100011 7
#430000
0*
#435000
b1101 S
1*
#436000
b11100111 7
#437000
b11101001 7
#440000
0*
#445000
b1100 S
1*
#446000
b11101101 7
#447000
b11101111 7
#450000
0*
#455000
b1011 S
1*
#456000
b11110011 7
#457000
b11110101 7
#460000
0*
#465000
b1010 S
1*
#466000
b11111001 7
#467000
b11111011 7
#470000
0*
#475000
b1001 S
1*
#476000
b11111111 7
#477000
b100000001 7
#480000
0*
#485000
b1000 S
1*
#486000
b100000101 7
#487000
b100000111 7
#490000
0*
#495000
b111 S
1*
#496000
b100001011 7
#497000
b100001101 7
#500000
0*
#505000
b110 S
1*
#506000
b100010001 7
#507000
b100010011 7
#510000
0*
#515000
b101 S
1*
#516000
b100010111 7
#517000
b100011001 7
#520000
0*
#525000
b100 S
1*
#526000
b100011101 7
#527000
b100011111 7
#530000
0*
#535000
b11 S
1*
#536000
b100100011 7
#537000
b100100101 7
#540000
0*
#545000
b10 S
1*
#546000
b100101001 7
#547000
b100101011 7
#550000
0*
#555000
b1 S
1*
#556000
b100101111 7
#557000
b100110001 7
#560000
0*
#565000
b0 S
1*
#566000
b100110101 7
#567000
b100110111 7
#570000
0*
#575000
b11 Q
b1111101001 R
b1111 S
1*
#576000
b100111011 7
#577000
b100111101 7
#580000
0*
#585000
b1110 S
1*
#586000
b101000001 7
#587000
b101000011 7
#590000
0*
#595000
b1101 S
1*
#596000
b101000111 7
#597000
b101001001 7
#600000
0*
#605000
b1100 S
1*
#606000
b101001101 7
#607000
b101001111 7
#610000
0*
#615000
b1011 S
1*
#616000
b101010011 7
#617000
b101010101 7
#620000
0*
#625000
b1010 S
1*
#626000
b101011001 7
#627000
b101011011 7
#630000
0*
#635000
b1001 S
1*
#636000
b101011111 7
#637000
b101100001 7
#640000
0*
#645000
b1000 S
1*
#646000
b101100101 7
#647000
b101100111 7
#650000
0*
#655000
b111 S
1*
#656000
b101101011 7
#657000
b101101101 7
#660000
0*
#665000
b110 S
1*
#666000
b101110001 7
#667000
b101110011 7
#670000
0*
#675000
b101 S
1*
#676000
b101110111 7
#677000
b101111001 7
#680000
0*
#685000
b100 S
1*
#686000
b101111101 7
#687000
b101111111 7
#690000
0*
#695000
b11 S
1*
#696000
b110000011 7
#697000
b110000101 7
#700000
0*
#705000
b10 S
1*
#706000
b110001001 7
#707000
b110001011 7
#710000
0*
#715000
b1 S
1*
#716000
b110001111 7
#717000
b110010001 7
#720000
0*
#725000
b0 S
1*
#726000
b110010101 7
#727000
b110010111 7
#730000
0*
#735000
0"
b100 Q
b1111110100 R
b1111 S
1*
#736000
b110011011 7
#737000
b110011101 7
#740000
0*
#745000
b1110 S
1*
#746000
b110100001 7
#747000
b110100011 7
#750000
0*
#755000
b1101 S
1*
#756000
b110100111 7
#757000
b110101001 7
#760000
0*
#765000
b1100 S
1*
#766000
b110101101 7
#767000
b110101111 7
#770000
0*
#775000
b1011 S
1*
#776000
b110110011 7
#777000
b110110101 7
#780000
0*
#785000
b1010 S
1*
#786000
b110111001 7
#787000
b110111011 7
#790000
0*
#795000
b1001 S
1*
#796000
b110111111 7
#797000
b111000001 7
#800000
0*
#805000
b1000 S
1*
#806000
b111000101 7
#807000
b111000111 7
#810000
0*
#815000
b111 S
1*
#816000
b111001011 7
#817000
b111001101 7
#820000
0*
#825000
b110 S
1*
#826000
b111010001 7
#827000
b111010011 7
#830000
0*
#835000
b101 S
1*
#836000
b111010111 7
#837000
b111011001 7
#840000
0*
#845000
b100 S
1*
#846000
b111011101 7
#847000
b111011111 7
#850000
0*
#855000
b11 S
1*
#856000
b111100011 7
#857000
b111100101 7
#860000
0*
#865000
b10 S
1*
#866000
b111101001 7
#867000
b111101011 7
#870000
0*
#875000
b1 S
1*
#876000
b111101111 7
#877000
b111110001 7
#880000
0*
#885000
b0 S
1*
#886000
b111110101 7
#887000
b111110111 7
#890000
0*
#895000
b101 Q
b1111111010 R
b1111 S
1*
#896000
b111111011 7
#897000
b111111101 7
#900000
0*
#905000
b1110 S
1*
#906000
b1000000001 7
#907000
b1000000011 7
#910000
0*
#915000
b1101 S
1*
#916000
b1000000111 7
#917000
b1000001001 7
#920000
0*
#925000
b1100 S
1*
#926000
b1000001101 7
#927000
b1000001111 7
#930000
0*
#935000
b1011 S
1*
#936000
b1000010011 7
#937000
b1000010101 7
#940000
0*
#945000
b1010 S
1*
#946000
b1000011001 7
#947000
b1000011011 7
#950000
0*
#955000
b1001 S
1*
#956000
b1000011111 7
#957000
b1000100001 7
#960000
0*
#965000
b1000 S
1*
#966000
b1000100101 7
#967000
b1000100111 7
#970000
0*
#975000
b111 S
1*
#976000
b1000101011 7
#977000
b1000101101 7
#980000
0*
#985000
b110 S
1*
#986000
b1000110001 7
#987000
b1000110011 7
#990000
0*
#995000
b101 S
1*
#996000
b1000110111 7
#997000
b1000111001 7
#1000000
0*
#1005000
b100 S
1*
#1006000
b1000111101 7
#1007000
b1000111111 7
#1010000
0*
#1015000
b11 S
1*
#1016000
b1001000011 7
#1017000
b1001000101 7
#1020000
0*
#1025000
b10 S
1*
#1026000
b1001001001 7
#1027000
b1001001011 7
#1030000
0*
#1035000
b1 S
1*
#1036000
b1001001111 7
#1037000
b1001010001 7
#1040000
0*
#1045000
b0 S
1*
#1046000
b1001010101 7
#1047000
b1001010111 7
#1050000
0*
#1055000
1"
b110 Q
b1111111101 R
b1111 S
1*
#1056000
b1001011011 7
#1057000
b1001011101 7
#1060000
0*
#1065000
b1110 S
1*
#1066000
b1001100001 7
#1067000
b1001100011 7
#1070000
0*
#1075000
b1101 S
1*
#1076000
b1001100111 7
#1077000
b1001101001 7
#1080000
0*
#1085000
b1100 S
1*
#1086000
b1001101101 7
#1087000
b1001101111 7
#1090000
0*
#1095000
b1011 S
1*
#1096000
b1001110011 7
#1097000
b1001110101 7
#1100000
0*
#1105000
b1010 S
1*
#1106000
b1001111001 7
#1107000
b1001111011 7
#1110000
0*
#1115000
b1001 S
1*
#1116000
b1001111111 7
#1117000
b1010000001 7
#1120000
0*
#1125000
b1000 S
1*
#1126000
b1010000101 7
#1127000
b1010000111 7
#1130000
0*
#1135000
b111 S
1*
#1136000
b1010001011 7
#1137000
b1010001101 7
#1140000
0*
#1145000
b110 S
1*
#1146000
b1010010001 7
#1147000
b1010010011 7
#1150000
0*
#1155000
b101 S
1*
#1156000
b1010010111 7
#1157000
b1010011001 7
#1160000
0*
#1165000
b100 S
1*
#1166000
b1010011101 7
#1167000
b1010011111 7
#1170000
0*
#1175000
b11 S
1*
#1176000
b1010100011 7
#1177000
b1010100101 7
#1180000
0*
#1185000
b10 S
1*
#1186000
b1010101001 7
#1187000
b1010101011 7
#1190000
0*
#1195000
b1 S
1*
#1196000
b1010101111 7
#1197000
b1010110001 7
#1200000
0*
#1205000
b0 S
1*
#1206000
b1010110101 7
#1207000
b1010110111 7
#1210000
0*
#1215000
0"
b111 Q
b1111111110 R
b1111 S
1*
#1216000
b1010111011 7
#1217000
b1010111101 7
#1220000
0*
#1225000
b1110 S
1*
#1226000
b1011000001 7
#1227000
b1011000011 7
#1230000
0*
#1235000
b1101 S
1*
#1236000
b1011000111 7
#1237000
b1011001001 7
#1240000
0*
#1245000
b1100 S
1*
#1246000
b1011001101 7
#1247000
b1011001111 7
#1250000
0*
#1255000
b1011 S
1*
#1256000
b1011010011 7
#1257000
b1011010101 7
#1260000
0*
#1265000
b1010 S
1*
#1266000
b1011011001 7
#1267000
b1011011011 7
#1270000
0*
#1275000
b1001 S
1*
#1276000
b1011011111 7
#1277000
b1011100001 7
#1280000
0*
#1285000
b1000 S
1*
#1286000
b1011100101 7
#1287000
b1011100111 7
#1290000
0*
#1295000
b111 S
1*
#1296000
b1011101011 7
#1297000
b1011101101 7
#1300000
0*
#1305000
b110 S
1*
#1306000
b1011110001 7
#1307000
b1011110011 7
#1310000
0*
#1315000
b101 S
1*
#1316000
b1011110111 7
#1317000
b1011111001 7
#1320000
0*
#1325000
b100 S
1*
#1326000
b1011111101 7
#1327000
b1011111111 7
#1330000
0*
#1335000
b11 S
1*
#1336000
b1100000011 7
#1337000
b1100000101 7
#1340000
0*
#1345000
b10 S
1*
#1346000
b1100001001 7
#1347000
b1100001011 7
#1350000
0*
#1355000
b1 S
1*
#1356000
b1100001111 7
#1357000
b1100010001 7
#1360000
0*
#1365000
b0 S
1*
#1366000
b1100010101 7
#1367000
b1100010111 7
#1370000
0*
#1375000
1"
b1000 Q
b1111111111 R
b1111 S
1*
#1376000
b1100011011 7
#1377000
b1100011101 7
#1380000
0*
#1385000
b1110 S
1*
#1386000
b1100100001 7
#1387000
b1100100011 7
#1390000
0*
#1395000
b1101 S
1*
#1396000
b1100100111 7
#1397000
b1100101001 7
#1400000
0*
#1405000
b1100 S
1*
#1406000
b1100101101 7
#1407000
b1100101111 7
#1410000
0*
#1415000
b1011 S
1*
#1416000
b1100110011 7
#1417000
b1100110101 7
#1420000
0*
#1425000
b1010 S
1*
#1426000
b1100111001 7
#1427000
b1100111011 7
#1430000
0*
#1435000
b1001 S
1*
#1436000
b1100111111 7
#1437000
b1101000001 7
#1440000
0*
#1445000
b1000 S
1*
#1446000
b1101000101 7
#1447000
b1101000111 7
#1450000
0*
#1455000
b111 S
1*
#1456000
b1101001011 7
#1457000
b1101001101 7
#1460000
0*
#1465000
b110 S
1*
#1466000
b1101010001 7
#1467000
b1101010011 7
#1470000
0*
#1475000
b101 S
1*
#1476000
b1101010111 7
#1477000
b1101011001 7
#1480000
0*
#1485000
b100 S
1*
#1486000
b1101011101 7
#1487000
b1101011111 7
#1490000
0*
#1495000
b11 S
1*
#1496000
b1101100011 7
#1497000
b1101100101 7
#1500000
0*
#1505000
b10 S
1*
#1506000
b1101101001 7
#1507000
b1101101011 7
#1510000
0*
#1515000
b1 S
1*
#1516000
b1101101111 7
#1517000
b1101110001 7
#1520000
0*
#1525000
b0 S
1*
#1526000
b1101110101 7
#1527000
b1101110111 7
#1530000
0*
#1535000
b1001 Q
b1111 S
1*
#1536000
b1101111011 7
#1537000
b1101111101 7
#1540000
0*
#1545000
b1110 S
1*
#1546000
b1110000001 7
#1547000
b1110000011 7
#1550000
0*
#1555000
b1101 S
1*
#1556000
b1110000111 7
#1557000
b1110001001 7
#1560000
0*
#1565000
b1100 S
1*
#1566000
b1110001101 7
#1567000
b1110001111 7
#1570000
0*
#1575000
b1011 S
1*
#1576000
b1110010011 7
#1577000
b1110010101 7
#1580000
0*
#1585000
b1010 S
1*
#1586000
b1110011001 7
#1587000
b1110011011 7
#1590000
0*
#1595000
b1001 S
1*
#1596000
b1110011111 7
#1597000
b1110100001 7
#1600000
0*
#1605000
b1000 S
1*
#1606000
b1110100101 7
#1607000
b1110100111 7
#1610000
0*
#1615000
b111 S
1*
#1616000
b1110101011 7
#1617000
b1110101101 7
#1620000
0*
#1625000
b110 S
1*
#1626000
b1110110001 7
#1627000
b1110110011 7
#1630000
0*
#1635000
b101 S
1*
#1636000
b1110110111 7
#1637000
b1110111001 7
#1640000
0*
#1645000
b100 S
1*
#1646000
b1110111101 7
#1647000
b1110111111 7
#1650000
0*
#1655000
b11 S
1*
#1656000
b1111000011 7
#1657000
b1111000101 7
#1660000
0*
#1665000
b10 S
1*
#1666000
b1111001001 7
#1667000
b1111001011 7
#1670000
0*
#1675000
b1 S
1*
#1676000
b1111001111 7
#1677000
b1111010001 7
#1680000
0*
#1685000
b0 S
1*
#1686000
b1111010101 7
#1687000
b1111010111 7
#1690000
0*
#1695000
1!
1#
0$
b1111 S
1*
#1696000
1,
b1111011011 7
#1697000
b1 >
b10000000000000000000000000000000000000000000000000000000000000000000000000000000000000000000000000000000000000000000000000000000000000000000000000000000000000000000000 3
b1111011100 7
#1700000
0*
#1703000
00
#1705000
0#
0I
1*
#1706000
0,
b1111100000 7
#1710000
0*
#1715000
0J
1*
#1716000
b1111100100 7
#1720000
0*
#1725000
1(
b1 L
b111 M
1*
#1726000
b1111101000 7
#1730000
0*
#1735000
b110 M
1*
#1736000
b1111101100 7
#1740000
0*
#1745000
b101 M
1*
#1746000
b1111110000 7
#1750000
0*
#1755000
b100 M
1*
#1756000
b1111110100 7
#1760000
0*
#1765000
b11 M
1*
#1766000
b1111111000 7
#1770000
0*
#1775000
b10 M
1*
#1776000
b1111111100 7
#1780000
0*
#1785000
b1 M
1*
#1786000
b10000000000 7
#1790000
0*
#1795000
b0 M
1*
#1796000
b10000000100 7
#1800000
0*
#1805000
b10 L
b1111 M
1*
#1806000
b10000001000 7
#1810000
0*
#1815000
b1110 M
1*
#1816000
b10000001100 7
#1820000
0*
#1825000
b1101 M
1*
#1826000
b10000010000 7
#1830000
0*
#1835000
b1100 M
1*
#1836000
b10000010100 7
#1840000
0*
#1845000
b1011 M
1*
#1846000
b10000011000 7
#1850000
0*
#1855000
b1010 M
1*
#1856000
b10000011100 7
#1860000
0*
#1865000
b1001 M
1*
#1866000
b10000100000 7
#1870000
0*
#1875000
b1000 M
1*
#1876000
b10000100100 7
#1880000
0*
#1885000
b111 M
1*
#1886000
b10000101000 7
#1890000
0*
#1895000
b110 M
1*
#1896000
b10000101100 7
#1900000
0*
#1905000
b101 M
1*
#1906000
b10000110000 7
#1910000
0*
#1915000
b100 M
1*
#1916000
b10000110100 7
#1920000
0*
#1925000
b11 M
1*
#1926000
b10000111000 7
#1930000
0*
#1935000
b10 M
1*
#1936000
b10000111100 7
#1940000
0*
#1945000
b1 M
1*
#1946000
b10001000000 7
#1950000
0*
#1955000
b0 M
1*
#1956000
b10001000100 7
#1960000
0*
#1965000
b1 G
b1111 M
1*
#1966000
b10001001000 7
#1970000
0*
#1975000
b1110 M
1*
#1976000
b10001001100 7
#1980000
0*
#1985000
b1101 M
1*
#1986000
b10001010000 7
#1990000
0*
#1995000
b1100 M
1*
#1996000
b10001010100 7
#2000000
0*
#2005000
b1011 M
1*
#2006000
b10001011000 7
#2010000
0*
#2015000
b1010 M
1*
#2016000
b10001011100 7
#2020000
0*
#2025000
b1001 M
1*
#2026000
b10001100000 7
#2030000
0*
#2035000
b1000 M
1*
#2036000
b10001100100 7
#2040000
0*
#2045000
b111 M
1*
#2046000
b10001101000 7
#2050000
0*
